receptor.v
module mdio_receptor (
    input wire MDC,
    input wire RESET,
    input wire MDIO_OUT,
    input wire MDIO_OE,
    output reg MDIO_DONE,
    output reg MDIO_IN,
    output reg [4:0] ADDR,
    output reg [15:0] WR_DATA,
    output reg WR_STB

);
    reg [15:0] RD_DATA;
    reg [3:0] state;
    reg [5:0] counter;      //debe contar de 0 hasta 31 (5bits)
    reg [15:0] mem [0:31];   // Memoria
    reg [1:0] tipo;
    
    integer i;
    initial begin
        for (i = 0; i < 32; i = i + 1) begin
            mem[i] = 16'b0;
            if (i==3) begin   //En la posición 3 de memoria almacenamos AAAA
                mem[i] = 16'h3AAA;
            end
        end
    end

    localparam IDLE = 4'd1, // One hot
               READ = 4'd2,
               WRITE = 4'd4,
               ACTIVE = 4'd8;


    always @(posedge MDC or negedge RESET) begin
    if (!RESET) begin  //RESET activo en bajo
        MDIO_DONE <= 0;
        MDIO_IN <= 0;
        ADDR <= 0;
        WR_DATA <= 0;
        WR_STB <= 0;
        counter <= 0;
        state <= IDLE;

        end else begin
        case (state)
            ACTIVE: begin 
                if( counter >=2 && counter < 4 ) begin
                    tipo[3-counter]<=MDIO_OUT;
                end
                if( counter >=4 && counter < 9 )  begin
                    ADDR[8-counter] <= MDIO_OUT;
                end
                if (counter>=16 && tipo == 2'b01) begin
                    WR_DATA[31-counter] <= MDIO_OUT;
                end
                if (counter>=16 && tipo == 2'b10) begin
                    RD_DATA <= mem[ADDR];
                end
                counter <= counter+1;
            end

            READ: begin
                MDIO_IN <= RD_DATA[31-counter];
                counter <= counter+1;
            end 

        endcase
        end
    end 

// logica de proximo estado
always @(posedge MDC) begin
    case (state)
        IDLE: begin
            MDIO_DONE = 0;
            MDIO_IN = 0;
            ADDR = 0;
            WR_DATA = 0;
            WR_STB = 0;
            counter = 0;
            tipo=0;

            if (MDIO_OE) begin
                state = ACTIVE;
            end
            else begin
                state = IDLE;
            end   
        end

        ACTIVE: begin
            if (tipo == 2'b10 && counter>=16) begin
                state = READ;
                end 
            if (tipo == 2'b01 && counter>=32) begin
                WR_STB = 1;
                state = WRITE;
            end 
            else if (counter>=32) begin
                state = IDLE;
            end
        end
        
        WRITE: begin
            MDIO_DONE = 1;
            mem[ADDR] = WR_DATA;
            state = IDLE;
        end

        READ: begin
            if (counter>=31) begin
            MDIO_DONE = 1;
            state = IDLE;
            end
        end

    endcase 
end 

endmodule

tester_receptor.v
`include "receptor.v"

module tb_mdio_receptor;
    reg MDC;
    reg RESET;
    reg MDIO_OUT;
    reg MDIO_OE;
    wire MDIO_DONE;
    wire MDIO_IN;
    input [4:0] ADDR;
    input [15:0] WR_DATA;
    wire WR_STB;

    mdio_receptor uut (
        .MDC(MDC),
        .RESET(RESET),
        .MDIO_OUT(MDIO_OUT),
        .MDIO_OE(MDIO_OE),
        .MDIO_DONE(MDIO_DONE),
        .MDIO_IN(MDIO_IN),
        .ADDR(ADDR),
        .WR_DATA(WR_DATA),
        .WR_STB(WR_STB)
    );

    initial begin
        // Initialize signals
        MDC = 0;
        RESET = 0;
        MDIO_OUT = 0;
        MDIO_OE = 0;
        #10 RESET = 1;

        // Simulate MDIO write transaction
        #5 MDIO_OE = 1;

        // Start bit
        #10 MDIO_OUT = 0;  
        #10 MDIO_OUT = 1;

        // Opcode (Write)
        #10 MDIO_OUT = 0;
        #10 MDIO_OUT = 1;

        // PHY address (7)
        #10 MDIO_OUT = 0;  
        #10 MDIO_OUT = 0;
        #10 MDIO_OUT = 1;
        #10 MDIO_OUT = 1;
        #10 MDIO_OUT = 1;

        // Register address and TA
        #10 MDIO_OUT = 1;  
        #10 MDIO_OUT = 0;
        #10 MDIO_OUT = 1;
        #10 MDIO_OUT = 0;
        #10 MDIO_OUT = 1;
        #10 MDIO_OUT = 1;
        #10 MDIO_OUT = 1; 
        
         // Data (43AE)
        #10 MDIO_OUT = 0;
        #10 MDIO_OUT = 1;
        #10 MDIO_OUT = 0;
        #10 MDIO_OUT = 0;

        #10 MDIO_OUT = 0;
        #10 MDIO_OUT = 0;
        #10 MDIO_OUT = 1;
        #10 MDIO_OUT = 1;

        #10 MDIO_OUT = 1;
        #10 MDIO_OUT = 0;
        #10 MDIO_OUT = 1;
        #10 MDIO_OUT = 0;

        #10 MDIO_OUT = 1;
        #10 MDIO_OUT = 1;
        #10 MDIO_OUT = 1;  
        #10 MDIO_OUT = 0;
        MDIO_OE = 0;


        // Simulate MDIO read transaction
        // Start bit
        #100 MDIO_OE = 1;

        // Start bit
        #10 MDIO_OUT = 0;  
        #10 MDIO_OUT = 1;

        // Opcode (Read)
        #10 MDIO_OUT = 1;
        #10 MDIO_OUT = 0;

        // PHY address (3)
        #10 MDIO_OUT = 0;  
        #10 MDIO_OUT = 0;
        #10 MDIO_OUT = 0;
        #10 MDIO_OUT = 1;
        #10 MDIO_OUT = 1;

        // Register address and TA
        #10 MDIO_OUT = 1;  
        #10 MDIO_OUT = 0;
        #10 MDIO_OUT = 1;
        #10 MDIO_OUT = 0;
        #10 MDIO_OUT = 1;
        #10 MDIO_OUT = 1;
        #10 MDIO_OUT = 1; 
        MDIO_OE = 0;

        #300 $finish;
    end

    always #5 MDC = ~MDC;

    initial begin
        $dumpfile("tb.vcd");
        $dumpvars;
        $dumpvars(0, uut.mem[7]);
        $dumpvars(0, uut.mem[3]);

    end
endmodule

tb.vcd
$date
	Thu Jun 27 21:05:56 2024
$end
$version
	Icarus Verilog
$end
$timescale
	1s
$end
$scope module tb_mdio_receptor $end
$var wire 1 ! WR_STB $end
$var wire 16 " WR_DATA [15:0] $end
$var wire 1 # MDIO_IN $end
$var wire 1 $ MDIO_DONE $end
$var wire 5 % ADDR [4:0] $end
$var reg 1 & MDC $end
$var reg 1 ' MDIO_OE $end
$var reg 1 ( MDIO_OUT $end
$var reg 1 ) RESET $end
$scope module uut $end
$var wire 1 & MDC $end
$var wire 1 ' MDIO_OE $end
$var wire 1 ( MDIO_OUT $end
$var wire 1 ) RESET $end
$var reg 5 * ADDR [4:0] $end
$var reg 1 $ MDIO_DONE $end
$var reg 1 # MDIO_IN $end
$var reg 16 + RD_DATA [15:0] $end
$var reg 16 , WR_DATA [15:0] $end
$var reg 1 ! WR_STB $end
$var reg 6 - counter [5:0] $end
$var reg 4 . state [3:0] $end
$var reg 2 / tipo [1:0] $end
$var integer 32 0 i [31:0] $end
$upscope $end
$upscope $end
$scope module tb_mdio_receptor $end
$scope module uut $end
$var reg 16 1 \mem[7] [15:0] $end
$upscope $end
$upscope $end
$scope module tb_mdio_receptor $end
$scope module uut $end
$var reg 16 2 \mem[3] [15:0] $end
$upscope $end
$upscope $end
$enddefinitions $end
#0
$dumpvars
b11101010101010 2
b0 1
b100000 0
bx /
b1 .
b0 -
b0 ,
bx +
b0 *
0)
0(
0'
0&
b0 %
0$
0#
b0 "
0!
$end
#5
b0 /
1&
#10
0&
1)
#15
b1000 .
1&
1'
#20
0&
#25
b1 -
1&
#30
0&
#35
b10 -
1&
1(
#40
0&
#45
b11 -
1&
0(
#50
0&
#55
b100 -
b1 /
1&
1(
#60
0&
#65
b101 -
1&
0(
#70
0&
#75
b110 -
1&
#80
0&
#85
b111 -
b100 %
b100 *
1&
1(
#90
0&
#95
b1000 -
b110 %
b110 *
1&
#100
0&
#105
b1001 -
b111 %
b111 *
1&
#110
0&
#115
b1010 -
1&
#120
0&
#125
b1011 -
1&
0(
#130
0&
#135
b1100 -
1&
1(
#140
0&
#145
b1101 -
1&
0(
#150
0&
#155
b1110 -
1&
1(
#160
0&
#165
b1111 -
1&
#170
0&
#175
b10000 -
1&
#180
0&
#185
b10001 -
1&
0(
#190
0&
#195
b10010 -
b100000000000000 "
b100000000000000 ,
1&
1(
#200
0&
#205
b10011 -
1&
0(
#210
0&
#215
b10100 -
1&
#220
0&
#225
b10101 -
1&
#230
0&
#235
b10110 -
1&
#240
0&
#245
b10111 -
b100001000000000 "
b100001000000000 ,
1&
1(
#250
0&
#255
b11000 -
b100001100000000 "
b100001100000000 ,
1&
#260
0&
#265
b11001 -
b100001110000000 "
b100001110000000 ,
1&
#270
0&
#275
b11010 -
1&
0(
#280
0&
#285
b11011 -
b100001110100000 "
b100001110100000 ,
1&
1(
#290
0&
#295
b11100 -
1&
0(
#300
0&
#305
b11101 -
b100001110101000 "
b100001110101000 ,
1&
1(
#310
0&
#315
b11110 -
b100001110101100 "
b100001110101100 ,
1&
#320
0&
#325
b11111 -
b100001110101110 "
b100001110101110 ,
1&
#330
0&
#335
b100000 -
1&
0'
0(
#340
0&
#345
b100001 -
b100 .
1!
1&
#350
0&
#355
b1 .
b100001110101110 1
1$
1&
#360
0&
#365
b0 /
b0 -
0!
b0 "
b0 ,
b0 %
b0 *
0$
1&
#370
0&
#375
1&
#380
0&
#385
1&
#390
0&
#395
1&
#400
0&
#405
1&
#410
0&
#415
1&
#420
0&
#425
1&
#430
0&
#435
b1000 .
1&
1'
#440
0&
#445
b1 -
1&
#450
0&
#455
b10 -
1&
1(
#460
0&
#465
b11 -
b10 /
1&
#470
0&
#475
b100 -
1&
0(
#480
0&
#485
b101 -
1&
#490
0&
#495
b110 -
1&
#500
0&
#505
b111 -
1&
#510
0&
#515
b1000 -
b10 %
b10 *
1&
1(
#520
0&
#525
b1001 -
b11 %
b11 *
1&
#530
0&
#535
b1010 -
1&
#540
0&
#545
b1011 -
1&
0(
#550
0&
#555
b1100 -
1&
1(
#560
0&
#565
b1101 -
1&
0(
#570
0&
#575
b1110 -
1&
1(
#580
0&
#585
b1111 -
1&
#590
0&
#595
b10000 -
1&
0'
#600
0&
#605
b10001 -
b11101010101010 +
b10 .
1&
#610
0&
#615
b10010 -
1&
#620
0&
#625
b10011 -
1#
1&
#630
0&
#635
b10100 -
1&
#640
0&
#645
b10101 -
1&
#650
0&
#655
b10110 -
0#
1&
#660
0&
#665
b10111 -
1#
1&
#670
0&
#675
b11000 -
0#
1&
#680
0&
#685
b11001 -
1#
1&
#690
0&
#695
b11010 -
0#
1&
#700
0&
#705
b11011 -
1#
1&
#710
0&
#715
b11100 -
0#
1&
#720
0&
#725
b11101 -
1#
1&
#730
0&
#735
b11110 -
0#
1&
#740
0&
#745
b11111 -
1#
1&
#750
0&
#755
b100000 -
0#
b1 .
1$
1&
#760
0&
#765
b0 /
b0 -
b0 %
b0 *
0$
1&
#770
0&
#775
1&
#780
0&
#785
1&
#790
0&
#795
1&
#800
0&
#805
1&
#810
0&
#815
1&
#820
0&
#825
1&
#830
0&
#835
1&
#840
0&
#845
1&
#850
0&
#855
1&
#860
0&
#865
1&
#870
0&
#875
1&
#880
0&
#885
1&
#890
0&
#895
1&
