receptor.v
module mdio_receptor (
    input wire MDC,
    input wire RESET,
    input wire MDIO_OUT,
    input wire MDIO_OE,
    input wire [15:0] RD_DATA,
    output reg MDIO_DONE,
    output reg MDIO_IN,
    output reg [4:0] ADDR,
    output reg [4:0] REGADR,
    output reg [15:0] WR_DATA,
    output reg WR_STB

);

    reg [3:0] state, prox_state;
     // registro interno que almacena los 32 bits del "frame" de la trans MDIO.
    reg [4:0] counter;            //debe contar de 0 hasta 31 (5bits)
    reg [15:0] mem [0:4];   // Memoria
    reg [1:0] tipo;
    
    localparam IDLE = 4'd1, // One hot
               WE = 4'd6,
               READ = 4'd2,
               WRITE = 4'd4,
               ACTIVE = 4'd8;


    // Propuesta: Tres estados: IDLE, lectura, escritura.
    always @(posedge MDC) begin
    if (!RESET) begin  //RESET activo en bajo
        MDIO_DONE <= 0;
        MDIO_IN <= 0;
        ADDR <= 0;
        REGADR <=0;
        WR_DATA <= 0;
        WR_STB <= 0;
        counter <= 0;
        state <= IDLE;
        end
    else begin
        state <= prox_state;
    end
    end 

//comunicacion usando el clk: mdc
always @(posedge MDC) begin     
    case (state)
        ACTIVE:begin 
            if( counter >=2 && counter < 4 ) begin
                tipo[3-counter]<=MDIO_OUT;
                $display(counter);
            end
            if( counter >=4 && counter < 9 )  begin
                ADDR[9-counter] <= MDIO_OUT;
            end
            counter <= counter+1;
        end

        READ: begin
            //frame[31-counter] <= MDIO_OUT; // del cpu al generador
            counter <= counter+1;
             if ( counter>=0 && counter <= 16) begin
                if(MDIO_DONE) begin// lo que envia el phy al receptor, y el receptor devuelve al gen por mdio_in
                MDIO_IN <= RD_DATA;
                end
             end
        end 

        WRITE: begin // escritura en alto los primeros 16 bits
            if (counter>=16) begin
            WR_DATA[31-counter] <= MDIO_OUT;
            end
            counter <= counter+1;
        end
    endcase
end

// logica de proximo estado y salidas
always @(*) begin
    //valor por defecto:
    prox_state = state;

    case (state)
        IDLE: begin
            if (MDIO_OE) begin
                prox_state = ACTIVE;
            end       
        end
        ACTIVE: begin
            if (tipo == 2'b10)begin
                prox_state = READ;
                end 
            else if (tipo == 2'b01 && counter>9) begin
                prox_state = WRITE;
            end 
            else if (counter == 32)begin
                 prox_state = IDLE;
            end
        end
        WRITE: begin
            if (counter == 32) begin
                state <= WE;
                MDIO_DONE<=1;
                WR_STB<=1;
            end
        end
        WE: begin
            mem[ADDR] <= WR_DATA;
            MDIO_DONE<=0;
            WR_STB<=0;
            prox_state=IDLE;
        end

        READ: begin
        end
    endcase 
end 
endmodule

tester_receptor.v
`include "receptor.v"

module tb_mdio_receptor;
    reg MDC;
    reg RESET;
    reg MDIO_OUT;
    reg MDIO_OE;
    wire MDIO_DONE;
    wire MDIO_IN;
    input [4:0] ADDR;
    input [15:0] WR_DATA;
    reg [15:0] RD_DATA;
    wire WR_STB;

    mdio_receptor uut (
        .MDC(MDC),
        .RESET(RESET),
        .MDIO_OUT(MDIO_OUT),
        .MDIO_OE(MDIO_OE),
        .MDIO_DONE(MDIO_DONE),
        .MDIO_IN(MDIO_IN),
        .ADDR(ADDR),
        .WR_DATA(WR_DATA),
        .RD_DATA(RD_DATA),
        .WR_STB(WR_STB)
    );

    initial begin
        // Initialize signals
        MDC = 0;
        RESET = 0;
        MDIO_OUT = 0;
        MDIO_OE = 0;
        RD_DATA = 16'hABCD;
        #10 RESET = 1;

        // Simulate MDIO write transaction
        MDIO_OE = 1;
        #5 MDIO_OUT = 1;  // Start bit
        #8 MDIO_OUT = 0;  // Opcode (Write)
        #4 MDIO_OUT = 1;
        #9 MDIO_OUT = 0;
        #6 MDIO_OUT = 0;  // PHY address
        #11 MDIO_OUT = 1;
        #15 MDIO_OUT = 1;
        #11 MDIO_OUT = 0;
        #10 MDIO_OUT = 1;
        #10 MDIO_OUT = 1;  // Register address
        #10 MDIO_OUT = 0;
        #10 MDIO_OUT = 1;
        #10 MDIO_OUT = 0;
        #10 MDIO_OUT = 1;
        #10 MDIO_OUT = 1;
        #10 MDIO_OUT = 1;  // Data
        #10 MDIO_OUT = 0;
        #10 MDIO_OUT = 1;
        #10 MDIO_OUT = 0;
        #10 MDIO_OUT = 1;
        #10 MDIO_OUT = 1;
        #10 MDIO_OUT = 1;
        #10 MDIO_OUT = 0;
        #10 MDIO_OUT = 1;
        #10 MDIO_OUT = 0;
        #10 MDIO_OUT = 1;
        #10 MDIO_OUT = 1;
        #10 MDIO_OUT = 1;  // Stop bit
        #10 MDIO_OUT = 0;

        // Simulate MDIO read transaction
        #50;
        MDIO_OE = 1;
        #10 MDIO_OUT = 1;  // Start bit
        #10 MDIO_OUT = 0;  // Opcode (Read)
        #10 MDIO_OUT = 1;
        #10 MDIO_OUT = 1;
        #10 MDIO_OUT = 0;
        #10 MDIO_OUT = 1;  // PHY address
        #10 MDIO_OUT = 0;
        #10 MDIO_OUT = 1;
        #10 MDIO_OUT = 0;
        #10 MDIO_OUT = 1;
        #10 MDIO_OUT = 1;  // Register address
        #10 MDIO_OUT = 0;
        #10 MDIO_OUT = 1;
        #10 MDIO_OUT = 0;
        #10 MDIO_OUT = 1;
        #10 MDIO_OUT = 1;
        #10 MDIO_OUT = 1;  // Data
        #10 MDIO_OUT = 0;
        #10 MDIO_OUT = 1;
        #10 MDIO_OUT = 0;
        #10 MDIO_OUT = 1;
        #10 MDIO_OUT = 1;
        #10 MDIO_OUT = 1;
        #10 MDIO_OUT = 0;
        #10 MDIO_OUT = 1;
        #10 MDIO_OUT = 0;
        #10 MDIO_OUT = 1;
        #10 MDIO_OUT = 1;
        #10 MDIO_OUT = 1;  // Stop bit
        #10 MDIO_OUT = 0;

        #100 $finish;
    end

    always #5 MDC = ~MDC;

    initial begin
        $dumpfile("tb.vcd");
        $dumpvars;
    end
endmodule

tb.vcd
$date
	Tue Jun 25 19:52:07 2024
$end
$version
	Icarus Verilog
$end
$timescale
	1s
$end
$scope module tb_mdio_receptor $end
$var wire 1 ! WR_STB $end
$var wire 16 " WR_DATA [15:0] $end
$var wire 1 # MDIO_IN $end
$var wire 1 $ MDIO_DONE $end
$var wire 5 % ADDR [4:0] $end
$var reg 1 & MDC $end
$var reg 1 ' MDIO_OE $end
$var reg 1 ( MDIO_OUT $end
$var reg 16 ) RD_DATA [15:0] $end
$var reg 1 * RESET $end
$scope module uut $end
$var wire 1 & MDC $end
$var wire 1 ' MDIO_OE $end
$var wire 1 ( MDIO_OUT $end
$var wire 16 + RD_DATA [15:0] $end
$var wire 1 * RESET $end
$var reg 5 , ADDR [4:0] $end
$var reg 1 $ MDIO_DONE $end
$var reg 1 # MDIO_IN $end
$var reg 5 - REGADR [4:0] $end
$var reg 16 . WR_DATA [15:0] $end
$var reg 1 ! WR_STB $end
$var reg 5 / counter [4:0] $end
$var reg 4 0 prox_state [3:0] $end
$var reg 4 1 state [3:0] $end
$var reg 2 2 tipo [1:0] $end
$upscope $end
$upscope $end
$enddefinitions $end
#0
$dumpvars
bx 2
bx 1
bx 0
bx /
bx .
bx -
bx ,
b1010101111001101 +
0*
b1010101111001101 )
0(
0'
0&
bx %
x$
x#
bx "
x!
$end
#5
b1 0
b1 1
b0 /
0!
b0 "
b0 .
b0 -
b0 %
b0 ,
0#
0$
1&
#10
b1000 0
0&
1'
1*
#15
b1000 1
1&
1(
#20
0&
#23
0(
#25
b1 /
1&
#27
1(
#30
0&
#35
b10 /
1&
#36
0(
#40
0&
#45
b11 /
b0x 2
1&
#50
0&
#53
1(
#55
b100 /
b1 2
1&
#60
0&
#65
b101 /
1&
#70
0&
#75
b110 /
b10000 %
b10000 ,
1&
#79
0(
#80
0&
#85
b111 /
1&
#89
1(
#90
0&
#95
b1000 /
b10100 %
b10100 ,
1&
#100
0&
#105
b1001 /
b10110 %
b10110 ,
1&
#109
0(
#110
0&
#115
b100 0
b1010 /
1&
#119
1(
#120
0&
#125
b100 1
b1011 /
1&
#129
0(
#130
0&
#135
b1100 /
1&
#139
1(
#140
0&
#145
b1101 /
1&
#150
0&
#155
b1110 /
1&
#160
0&
#165
b1111 /
1&
#169
0(
#170
0&
#175
b10000 /
1&
#179
1(
#180
0&
#185
b10001 /
b1000000000000000 "
b1000000000000000 .
1&
#189
0(
#190
0&
#195
b10010 /
1&
#199
1(
#200
0&
#205
b10011 /
b1010000000000000 "
b1010000000000000 .
1&
#210
0&
#215
b10100 /
b1011000000000000 "
b1011000000000000 .
1&
#220
0&
#225
b10101 /
b1011100000000000 "
b1011100000000000 .
1&
#229
0(
#230
0&
#235
b10110 /
1&
#239
1(
#240
0&
#245
b10111 /
b1011101000000000 "
b1011101000000000 .
1&
#249
0(
#250
0&
#255
b11000 /
1&
#259
1(
#260
0&
#265
b11001 /
b1011101010000000 "
b1011101010000000 .
1&
#270
0&
#275
b11010 /
b1011101011000000 "
b1011101011000000 .
1&
#280
0&
#285
b11011 /
b1011101011100000 "
b1011101011100000 .
1&
#289
0(
#290
0&
#295
b11100 /
1&
#300
0&
#305
b11101 /
1&
#310
0&
#315
b11110 /
1&
#320
0&
#325
b11111 /
1&
#330
0&
#335
b0 /
1&
#340
0&
#345
b1 /
1&
#349
1(
#350
0&
#355
b10 /
1&
#359
0(
#360
0&
#365
b11 /
1&
#369
1(
#370
0&
#375
b100 /
1&
#380
0&
#385
b101 /
1&
#389
0(
#390
0&
#395
b110 /
1&
#399
1(
#400
0&
#405
b111 /
1&
#409
0(
#410
0&
#415
b1000 /
1&
#419
1(
#420
0&
#425
b1001 /
1&
#429
0(
#430
0&
#435
b1010 /
1&
#439
1(
#440
0&
#445
b1011 /
1&
#450
0&
#455
b1100 /
1&
#459
0(
#460
0&
#465
b1101 /
1&
#469
1(
#470
0&
#475
b1110 /
1&
#479
0(
#480
0&
#485
b1111 /
1&
#489
1(
#490
0&
#495
b10000 /
1&
#500
0&
#505
b10001 /
1&
#510
0&
#515
b10010 /
b1111101011100000 "
b1111101011100000 .
1&
#519
0(
#520
0&
#525
b10011 /
b1101101011100000 "
b1101101011100000 .
1&
#529
1(
#530
0&
#535
b10100 /
1&
#539
0(
#540
0&
#545
b10101 /
b1101001011100000 "
b1101001011100000 .
1&
#549
1(
#550
0&
#555
b10110 /
b1101011011100000 "
b1101011011100000 .
1&
#560
0&
#565
b10111 /
1&
#570
0&
#575
b11000 /
b1101011111100000 "
b1101011111100000 .
1&
#579
0(
#580
0&
#585
b11001 /
b1101011101100000 "
b1101011101100000 .
1&
#589
1(
#590
0&
#595
b11010 /
1&
#599
0(
#600
0&
#605
b11011 /
b1101011101000000 "
b1101011101000000 .
1&
#609
1(
#610
0&
#615
b11100 /
b1101011101010000 "
b1101011101010000 .
1&
#620
0&
#625
b11101 /
b1101011101011000 "
b1101011101011000 .
1&
#630
0&
#635
b11110 /
b1101011101011100 "
b1101011101011100 .
1&
#639
0(
#640
0&
#645
b11111 /
1&
#650
0&
#655
b0 /
1&
#660
0&
#665
b1 /
1&
#670
0&
#675
b10 /
1&
#680
0&
#685
b11 /
1&
#690
0&
#695
b100 /
1&
#700
0&
#705
b101 /
1&
#710
0&
#715
b110 /
1&
#720
0&
#725
b111 /
1&
#730
0&
#735
b1000 /
1&
